Workbook
Name IA: ENTREGAS!$A$4:$K$4

Sheet Asignaturas
A4: Código | B4: Sección | C4: Columna 1 | D4: Docentes | E4: Asignatura | G4: EVALUACIONES
A5: A1ADEE9 | B5: A | C5: =A5&B5 -> A1ADEE9A | D5: SUSSY DE LOS RIOS BOTTERI / | E5: EMPLOYEE EXPERIENCE | G5: Práctica 1
A6: A1AG1 | B6: A | C6: =A6&B6 -> A1AG1A | D6: ELSA MERCEDES ALAMA SALAZAR / | E6: FUNDAMENTOS DE ADMINISTRACIÓN 1 | G6: Práctica 2
A7: A1AG1 | B7: B | C7: =A7&B7 -> A1AG1B | D7: BEATRIZ ELVIRA VEGAS CHIYÓN / | E7: FUNDAMENTOS DE ADMINISTRACIÓN 1 | G7: Práctica 3
A8: A1AG1 | B8: C | C8: =A8&B8 -> A1AG1C | D8: BEATRIZ ELVIRA VEGAS CHIYÓN / | E8: FUNDAMENTOS DE ADMINISTRACIÓN 1 | G8: Práctica 4
A9: A1AG1 | B9: D | C9: =A9&B9 -> A1AG1D | D9: BEATRIZ ELVIRA VEGAS CHIYÓN / | E9: FUNDAMENTOS DE ADMINISTRACIÓN 1 | G9: Práctica 5
A10: A1AG2 | B10: A | C10: =A10&B10 -> A1AG2A | D10: CLAUDIA MARIA CHENG BARRANTES / | E10: FUNDAMENTOS DE ADMINISTRACIÓN 2 | G10: Parcial
A11: A1AG2 | B11: B | C11: =A11&B11 -> A1AG2B | D11: CLAUDIA MARIA CHENG BARRANTES / | E11: FUNDAMENTOS DE ADMINISTRACIÓN 2 | G11: Final
A12: A1AG3 | B12: A | C12: =A12&B12 -> A1AG3A | D12: FABIOLA ALCAS ROJAS / | E12: EMPRENDIMIENTO Y ESTRATEGIA | G12: Control 01
A13: A1AG3 | B13: B | C13: =A13&B13 -> A1AG3B | D13: FABIOLA ALCAS ROJAS / | E13: EMPRENDIMIENTO Y ESTRATEGIA | G13: Informe
A14: A1AG4 | B14: A | C14: =A14&B14 -> A1AG4A | D14: JUANA MARÍA HUACO GARCÍA / | E14: DISEÑO ORGANIZACIONAL | G14: Control 02
A15: A1AG4 | B15: B | C15: =A15&B15 -> A1AG4B | D15: JUANA MARÍA HUACO GARCÍA / | E15: DISEÑO ORGANIZACIONAL
A16: A1AG5 | B16: A | C16: =A16&B16 -> A1AG5A | D16: ELSA MERCEDES ALAMA SALAZAR / | E16: PSICOLOGÍA EN LAS ORGANIZACIONES | G16: Control 03
A17: A1AG5 | B17: B | C17: =A17&B17 -> A1AG5B | D17: ELSA MERCEDES ALAMA SALAZAR / | E17: PSICOLOGÍA EN LAS ORGANIZACIONES | G17: Control 04
A18: A1AG6 | B18: A | C18: =A18&B18 -> A1AG6A | D18: ALMA ROSA MACHUCA MAZA / | E18: DIRECCIÓN DE PERSONAL | G18: Control 05
A19: A1AG6 | B19: B | C19: =A19&B19 -> A1AG6B | D19: TEO ERNESTO MARTIN HIDALGO CORTES / | E19: DIRECCIÓN DE PERSONAL | G19: Control 06
A20: A1AGGE9 | B20: A | C20: =A20&B20 -> A1AGGE9A | D20: TEO ERNESTO MARTIN HIDALGO CORTES / | E20: GESTIÓN DE LA EMPLEABILIDAD | G20: Trabajo 01
A21: A1AGGI9 | B21: A | C21: =A21&B21 -> A1AGGI9A | D21: EDILBERTO LUIS PEDRO SALAZAR OSORES / | E21: GESTIÓN DE LA INNOVACIÓN | G21: Trabajo grupal
A22: A1AGIE9 | B22: A | C22: =A22&B22 -> A1AGIE9A | D22: CARLOS RODRICH / | E22: INNOVACIÓN EMPRESARIAL | G22: Participación
A23: A1BSA | B23: A | C23: =A23&B23 -> A1BSAA | D23: RICARDO ALBERTO ORMEÑO SÁNCHEZ / | E23: BUSINESS ANALYTICS | G23: Laboratorio
A24: A1BSA | B24: B | C24: =A24&B24 -> A1BSAB | D24: LUIS EGBERTO ALVARADO PINTADO / | E24: BUSINESS ANALYTICS | G24: Sustitutorio
A25: A1CC1 | B25: A | C25: =A25&B25 -> A1CC1A | D25: JORGE ARMANDO SANCHEZ FARFAN / | E25: CONTABILIDAD DE COSTOS | G25: REPROG P2
A26: A1CC1 | B26: B | C26: =A26&B26 -> A1CC1B | D26: YULLIANA MARISED LLAUCE ONTANEDA / | E26: CONTABILIDAD DE COSTOS | G26: REPROG P3
A27: A1CC2 | B27: A | C27: =A27&B27 -> A1CC2A | D27: SHIRLEY VANESSA TESEN SANDOVAL / | E27: COSTOS Y PRESUPUESTOS | G27: REPROG P4
... A47: A1ES2 | B47: A | C47: =A47&B47 -> A1ES2A | D47: LUIS EGBERTO ALVARADO PINTADO / | E47: ESTADÍSTICA 2 | G47: Trabajo grupal 1
A48: A1ES2 | B48: B | C48: =A48&B48 -> A1ES2B | D48: LUIS EGBERTO ALVARADO PINTADO / | E48: ESTADÍSTICA 2
A49: A1ETN | B49: A | C49: =A49&B49 -> A1ETNA | D49: MANUEL LÓPEZ ORTIZ / | E49: ÉTICA DE NEGOCIOS
A50: A1ETN | B50: B | C50: =A50&B50 -> A1ETNB | D50: MANUEL LÓPEZ ORTIZ / | E50: ÉTICA DE NEGOCIOS
A51: A1FP1 | B51: A | C51: =A51&B51 -> A1FP1A | D51: WILLIAN ALFREDO REYES CORTES / | E51: FUNDAMENTOS DE PROGRAMACIÓN
A52: A1FP1 | B52: B | C52: =A52&B52 -> A1FP1B | D52: WILLIAN ALFREDO REYES CORTES / | E52: FUNDAMENTOS DE PROGRAMACIÓN
A53: A1FP1 | B53: C | C53: =A53&B53 -> A1FP1C | D53: WILLIAN ALFREDO REYES CORTES / | E53: FUNDAMENTOS DE PROGRAMACIÓN
A54: A1FZ1 | B54: A | C54: =A54&B54 -> A1FZ1A | D54: JUAN RICARDO MATÍAS PALMA / | E54: METODOLOGÍA DE ESTUDIO
A55: A1FZ1 | B55: B | C55: =A55&B55 -> A1FZ1B | D55: JUAN RICARDO MATÍAS PALMA / | E55: METODOLOGÍA DE ESTUDIO
A56: A1FZ2 | B56: A | C56: =A56&B56 -> A1FZ2A | D56: RAFAEL ANTONIO VALERA MORENO / | E56: FINANZAS OPERATIVAS
A57: A1FZ2 | B57: B | C57: =A57&B57 -> A1FZ2B | D57: RAFAEL ANTONIO VALERA MORENO / | E57: FINANZAS OPERATIVAS
A58: A1FZ3 | B58: A | C58: =A58&B58 -> A1FZ3A | D58: JORGE EDUARDO GALLO COSTA / | E58: EVALUACIÓN DE INVERSIONES
A59: A1FZ3 | B59: B | C59: =A59&B59 -> A1FZ3B | D59: JORGE EDUARDO GALLO COSTA / | E59: EVALUACIÓN DE INVERSIONES
... A230: TE2 | B230: C | C230: =A230&B230 -> TE2C | D230: RICARDO GERMÁN GONZÁLEZ GATICA / | E230: TEOLOGÍA Y VIDA CRISTIANA
A231: MICR03002 | B231: A | C231: =A231&B231 -> MICR03002A | D231: GUSTAVO ALFREDO RIESCO LIND /
A232: MICR03002 | B232: A | C232: =A232&B232 -> MICR03002A | D232: GUSTAVO ALFREDO RIESCO LIND /
A233: FINZ03042 | B233: A | C233: =A233&B233 -> FINZ03042A | D233: JOSÉ FAUSTINO LUPU FIGALLO /
C234: =A234&B234
C235: =A235&B235
C236: =A236&B236
C237: =A237&B237
C238: =A238&B238
C239: =A239&B239
C240: =A240&B240
C241: =A241&B241
C242: =A242&B242
C243: =A243&B243
C244: =A244&B244
C245: =A245&B245
... C264: =A264&B264

Sheet ENTREGAS
A2: EVALUACIONES POR RECOGER
L3: ingrese reclamos
A4: SIGLA | B4: SECC | C4: BUSCAR | D4: DOCENTE | E4: EVALUACIÓN | F4: TURNO | G4: DÍA DE ENTREGA | H4: VCTO. DEL RECLAMO | I4: HORA | J4: RECOJO | K4: LUGAR | L4: N° RECLAMOS | M4: OBS. | N4: Columna1
A5: A1MK2 | B5: A | C5: =A5&B5 -> A1MK2A | D5: =VLOOKUP($C5,Asignaturas!$C$5:$D$261,2,0) -> VICTOR ALEJANDRO DE LA TORRE PALACIOS / | E5: Práctica 1 | F5: AM | G5: 46121 | H5: 46122 | I5: 1:00p.m. | J5: =+Tabla2[[#This Row],[DÍA DE ENTREGA]]+8 -> 46129 | K5: CLASE | L5: 1
A6: A1CC1 | B6: A | C6: =A6&B6 -> A1CC1A | D6: =VLOOKUP($C6,Asignaturas!$C$5:$D$261,2,0) -> JORGE ARMANDO SANCHEZ FARFAN / | E6: Control 1 | F6: AM | G6: 46121 | H6: 46122 | I6: 1:00p.m. | J6: =+Tabla2[[#This Row],[DÍA DE ENTREGA]]+8 -> 46129 | K6: CLASE | L6: 1
A7: MACR03004 | B7: A | C7: =A7&B7 -> MACR03004A | D7: =VLOOKUP($C7,Asignaturas!$C$5:$D$261,2,0) -> ZENÓN FIDEL QUISPE MISAICO / | E7: Práctica 1 | F7: AM | G7: 46122 | H7: 46126 | I7: 1:00p.m. | J7: =+Tabla2[[#This Row],[DÍA DE ENTREGA]]+8 -> 46130 | K7: VENTANILLA | L7: 0
A8: A1EC1 | B8: A | C8: =A8&B8 -> A1EC1A | D8: =VLOOKUP($C8,Asignaturas!$C$5:$D$261,2,0) -> INGRID CECILIA CASANA ORTEGA / | E8: Práctica 1 | F8: AM | G8: 46122 | H8: 46126 | I8: 1:00p.m. | J8: =+Tabla2[[#This Row],[DÍA DE ENTREGA]]+8 -> 46130 | K8: CLASE | L8: 0
A9: A1EC1 | B9: B | C9: =A9&B9 -> A1EC1B | D9: =VLOOKUP($C9,Asignaturas!$C$5:$D$261,2,0) -> INGRID CECILIA CASANA ORTEGA / | E9: Práctica 1 | F9: AM | G9: 46121 | H9: 46122 | I9: 1:00p.m. | J9: =+Tabla2[[#This Row],[DÍA DE ENTREGA]]+8 -> 46129 | K9: CLASE | L9: 0
A10: MATE03008 | B10: B | C10: =A10&B10 -> MATE03008B | D10: =VLOOKUP($C10,Asignaturas!$C$5:$D$261,2,0) -> JAVIER FARFÁN NAVARRO / | E10: Control 1 | F10: AM | G10: 46120 | H10: 46121 | I10: 6:30p.m. | J10: =+Tabla2[[#This Row],[DÍA DE ENTREGA]]+8 -> 46128 | K10: CLASE | L10: 1 | M10: AÚN NO LLEGAN LOS SOBRANTES
A11: AF1 | B11: A | C11: =A11&B11 -> AF1A | D11: =VLOOKUP($C11,Asignaturas!$C$5:$D$261,2,0) -> CLAUDIA MARÍA RIVERA TÁVARA / | E11: Control 1 | F11: PM | G11: 46122 | H11: 46126 | I11: 6:30p.m. | J11: =+Tabla2[[#This Row],[DÍA DE ENTREGA]]+8 -> 46130 | K11: CLASE
A12: CF4 | B12: A | C12: =A12&B12 -> CF4A | D12: =VLOOKUP($C12,Asignaturas!$C$5:$D$261,2,0) -> MARÍA CECILIA VENEGAS MORALES / | E12: Práctica 1 | F12: AM | G12: 46126 | H12: 46127 | I12: 1:00p.m. | J12: =+Tabla2[[#This Row],[DÍA DE ENTREGA]]+8 -> 46134 | K12: VENTANILLA | L12: 0
A13: HC1 | B13: C | C13: =A13&B13 -> HC1C | D13: =VLOOKUP($C13,Asignaturas!$C$5:$D$261,2,0) -> ADRIANA ISABEL LAOS LEVAGGI / | E13: Práctica 1 | F13: PM | G13: 46126 | H13: 46127 | I13: 6:30p.m. | J13: =+Tabla2[[#This Row],[DÍA DE ENTREGA]]+8 -> 46134 | K13: VENTANILLA | L13: 2
A14: ESTA03008 | B14: A | C14: =A14&B14 -> ESTA03008A | D14: =VLOOKUP($C14,Asignaturas!$C$5:$D$261,2,0) -> CRISTIAN ADDERLY MARAVI MENESES / | E14: Práctica 1 | F14: AM | G14: 46126 | H14: 46127 | I14: 1:00p.m. | J14: =+Tabla2[[#This Row],[DÍA DE ENTREGA]]+8 -> 46134 | K14: CLASE | L14: 2
A15: A1DPRT9 | B15: A | C15: =A15&B15 -> A1DPRT9A | D15: =VLOOKUP($C15,Asignaturas!$C$5:$D$261,2,0) -> MANUEL PRENDES GUARDIOLA / | E15: Práctica 1 | F15: PM | G15: 46126 | H15: 46127 | I15: 6:30p.m. | J15: =+Tabla2[[#This Row],[DÍA DE ENTREGA]]+8 -> 46134 | K15: CLASE | L15: 1
A16: FINZ03032 | B16: A | C16: =A16&B16 -> FINZ03032A | D16: =VLOOKUP($C16,Asignaturas!$C$5:$D$261,2,0) -> BRENDA SILUPÚ GARCÉS / SERGIO DAVID REYES LANDA / | E16: Práctica 1 | F16: AM | G16: 46127 | H16: 46128 | I16: 1:00p.m. | J16: =+Tabla2[[#This Row],[DÍA DE ENTREGA]]+8 -> 46135 | K16: CLASE | L16: 0
A17: MATE03008 | B17: A | C17: =A17&B17 -> MATE03008A | D17: =VLOOKUP($C17,Asignaturas!$C$5:$D$261,2,0) -> JAVIER FARFÁN NAVARRO / | E17: Práctica 1 | F17: AM | G17: 46127 | H17: 46128 | I17: 1:00p.m. | J17: =+Tabla2[[#This Row],[DÍA DE ENTREGA]]+8 -> 46135 | K17: CLASE | L17: 6
A18: MATE03008 | B18: C | C18: =A18&B18 -> MATE03008C | D18: =VLOOKUP($C18,Asignaturas!$C$5:$D$261,2,0) -> JAVIER FARFÁN NAVARRO / | E18: Práctica 1 | F18: AM | G18: 46127 | H18: 46128 | I18: 1:00p.m. | J18: =+Tabla2[[#This Row],[DÍA DE ENTREGA]]+8 -> 46135 | K18: CLASE | L18: 7
A19: MATE03009 | B19: A | C19: =A19&B19 -> MATE03009A | D19: =VLOOKUP($C19,Asignaturas!$C$5:$D$261,2,0) -> NESTOR FARÍAS / WILLIAN REYES | E19: Práctica 1 | F19: AM | G19: 46127 | H19: 46128 | I19: 1:00p.m. | J19: =+Tabla2[[#This Row],[DÍA DE ENTREGA]]+8 -> 46135 | K19: CLASE | L19: 5
A20: MACR03002 | B20: A | C20: =A20&B20 -> MACR03002A | D20: =VLOOKUP($C20,Asignaturas!$C$5:$D$261,2,0) -> LUIS ALONSO CASAVERDE ANTÓN / | E20: Práctica 1 | F20: AM | G20: 46128 | H20: 46129 | I20: 1:00p.m. | J20: =+Tabla2[[#This Row],[DÍA DE ENTREGA]]+8 -> 46136 | K20: CLASE | L20: 1
A21: A1CF2 | B21: B | C21: =A21&B21 -> A1CF2B | D21: =VLOOKUP($C21,Asignaturas!$C$5:$D$261,2,0) -> MARLON RAUL ALVIA SIANCAS / | E21: Control 01 | F21: AM | G21: 46128 | H21: 46129 | I21: 1:00p.m. | J21: =+Tabla2[[#This Row],[DÍA DE ENTREGA]]+8 -> 46136 | K21: CLASE | L21: 0
A22: GTH | B22: A | C22: =A22&B22 -> GTHA | D22: =VLOOKUP($C22,Asignaturas!$C$5:$D$261,2,0) -> JUANA MARÍA HUACO GARCÍA / TEO ERNESTO MARTIN HIDALGO CORTES / | E22: Práctica 1 | F22: AM | G22: 46129 | H22: 46132 | I22: 1:00p.m. | J22: =+Tabla2[[#This Row],[DÍA DE ENTREGA]]+8 -> 46137 | K22: VENTANILLA | L22: 0
A23: HC1 | B23: F | C23: =A23&B23 -> HC1F | D23: =VLOOKUP($C23,Asignaturas!$C$5:$D$261,2,0) -> JAVIER GOMEZ SANCHEZ / | E23: Práctica 1 | F23: AM | G23: 46128 | H23: 46129 | I23: 1:00p.m. | J23: =+Tabla2[[#This Row],[DÍA DE ENTREGA]]+8 -> 46136 | K23: CLASE | L23: 0
... A53: CF5 | B53: A | C53: =A53&B53 -> CF5A | D53: =VLOOKUP($C53,Asignaturas!$C$5:$D$261,2,0) -> MARÍA JESUS FARFÁN / IVETTE NUÑEZ LAGUNA | E53: Práctica 1 | F53: AM | G53: 46132 | H53: 46133 | I53: 1:00p.m. | J53: =+Tabla2[[#This Row],[DÍA DE ENTREGA]]+8 -> 46140 | K53: CLASE | L53: 0
A54: A1FZ1 | B54: A | C54: =A54&B54 -> A1FZ1A | D54: =VLOOKUP($C54,Asignaturas!$C$5:$D$261,2,0) -> JUAN RICARDO MATÍAS PALMA / | E54: Práctica 1 | F54: AM | G54: 46133 | H54: 46134 | I54: 1:00p.m. | J54: =+Tabla2[[#This Row],[DÍA DE ENTREGA]]+8 -> 46141 | K54: CLASE | L54: 3 | M54: AÚN NO LLEGAN LOS SOBRANTES
A55: MICR03005 | B55: A | C55: =A55&B55 -> MICR03005A | D55: =VLOOKUP($C55,Asignaturas!$C$5:$D$261,2,0) -> ALFONSO GUILLERMO DULANTO RISHING / | E55: Práctica 1 | F55: AM | G55: 46130 | H55: 46133 | I55: 1:00p.m. | J55: =+Tabla2[[#This Row],[DÍA DE ENTREGA]]+8 -> 46138 | K55: CLASE | L55: 6 | M55: AÚN NO LLEGAN LOS SOBRANTES
A56: M4DS | B56: A | C56: =A56&B56 -> M4DSA | D56: =VLOOKUP($C56,Asignaturas!$C$5:$D$261,2,0) -> LOURDES RENATA CORONADO GOMEZ / | E56: Taller 01 | F56: AM | G56: 46135 | H56: 46136 | I56: 1:00p.m. | J56: =+Tabla2[[#This Row],[DÍA DE ENTREGA]]+11 -> 46146 | K56: VENTANILLA | L56: 0
A57: A1CC1 | B57: A | C57: =A57&B57 -> A1CC1A | D57: =VLOOKUP($C57,Asignaturas!$C$5:$D$261,2,0) -> JORGE ARMANDO SANCHEZ FARFAN / | E57: Control 02 | F57: AM | G57: 46135 | H57: 46136 | I57: 1:00p.m. | J57: =+Tabla2[[#This Row],[DÍA DE ENTREGA]]+11 -> 46146 | K57: CLASE | L57: 0
A58: A1MK1 | B58: A | C58: =A58&B58 -> A1MK1A | D58: =VLOOKUP($C58,Asignaturas!$C$5:$D$261,2,0) -> GONZALO GUILLERMO AUGUSTO VOYSEST / | E58: Práctica 1 | F58: AM | G58: 46132 | H58: 46133 | I58: 1:00p.m. | J58: =+Tabla2[[#This Row],[DÍA DE ENTREGA]]+8 -> 46140 | K58: CLASE | L58: 0
A59: AF1 | B59: A | C59: =A59&B59 -> AF1A | D59: =VLOOKUP($C59,Asignaturas!$C$5:$D$261,2,0) -> CLAUDIA MARÍA RIVERA TÁVARA / | E59: Práctica 1 | F59: PM | G59: 46134 | H59: 46135 | I59: 6:30p.m. | J59: =+Tabla2[[#This Row],[DÍA DE ENTREGA]]+8 -> 46142 | K59: CLASE | L59: 0
A60: A1MK3 | B60: B | C60: =A60&B60 -> A1MK3B | D60: =VLOOKUP($C60,Asignaturas!$C$5:$D$261,2,0) -> ANA LUCÍA MARTÍNEZ AZCÁRATE / | E60: Controles | F60: AM | G60: 46135 | H60: 46136 | I60: 1:00p.m. | J60: =+Tabla2[[#This Row],[DÍA DE ENTREGA]]+11 -> 46146 | K60: VENTANILLA | L60: 0
A61: A1FZ2 | B61: A | C61: =A61&B61 -> A1FZ2A | D61: =VLOOKUP($C61,Asignaturas!$C$5:$D$261,2,0) -> RAFAEL ANTONIO VALERA MORENO / | E61: Práctica 1 | F61: AM | G61: 46135 | H61: 46136 | I61: 1:00p.m. | J61: =+Tabla2[[#This Row],[DÍA DE ENTREGA]]+11 -> 46146 | K61: VENTANILLA | L61: 1
A62: A1FZ2 | B62: B | C62: =A62&B62 -> A1FZ2B | D62: =VLOOKUP($C62,Asignaturas!$C$5:$D$261,2,0) -> RAFAEL ANTONIO VALERA MORENO / | E62: Práctica 1 | F62: AM | G62: 46135 | H62: 46136 | I62: 1:00p.m. | J62: =+Tabla2[[#This Row],[DÍA DE ENTREGA]]+11 -> 46146 | K62: VENTANILLA | L62: 1
A63: HC3 | B63: A | C63: =A63&B63 -> HC3A | D63: =VLOOKUP($C63,Asignaturas!$C$5:$D$261,2,0) -> JAVIER GOMEZ SANCHEZ / | E63: Práctica 1 | F63: AM | G63: 46134 | H63: 46135 | I63: 1:00p.m. | J63: =+Tabla2[[#This Row],[DÍA DE ENTREGA]]+8 -> 46142 | K63: CLASE | L63: 0
A64: RCO | B64: A | C64: =A64&B64 -> RCOA | D64: =VLOOKUP($C64,Asignaturas!$C$5:$D$261,2,0) -> FERNANDO ALFREDO RIOFRIO ZUÑIGA / | E64: Práctica 1 | F64: PM | G64: 46135 | H64: 46136 | I64: 6:30p.m. | J64: =+Tabla2[[#This Row],[DÍA DE ENTREGA]]+11 -> 46146 | K64: VENTANILLA | L64: 1
A65: RCO | B65: C | C65: =A65&B65 -> RCOC | D65: =VLOOKUP($C65,Asignaturas!$C$5:$D$261,2,0) -> FERNANDO ALFREDO RIOFRIO ZUÑIGA / | E65: Práctica 1 | F65: PM | G65: 46135 | H65: 46136 | I65: 6:30p.m. | J65: =+Tabla2[[#This Row],[DÍA DE ENTREGA]]+11 -> 46146 | K65: VENTANILLA | L65: 0
A66: A1CF1 | B66: B | C66: =A66&B66 -> A1CF1B | D66: =VLOOKUP($C66,Asignaturas!$C$5:$D$261,2,0) -> MARIA JESÚS FARFÁN MANRIQUE / | E66: Práctica 1 | F66: AM | G66: 46135 | H66: 46136 | I66: 1:00p.m. | J66: =+Tabla2[[#This Row],[DÍA DE ENTREGA]]+8 -> 46143 | K66: CLASE | L66: 2
A67: A1FZ1 | B67: B | C67: =A67&B67 -> A1FZ1B | D67: =VLOOKUP($C67,Asignaturas!$C$5:$D$261,2,0) -> JUAN RICARDO MATÍAS PALMA / | E67: Práctica 1 | F67: PM | G67: 46132 | H67: 46133 | I67: 6:30p.m. | J67: =+Tabla2[[#This Row],[DÍA DE ENTREGA]]+8 -> 46140 | K67: CLASE | L67: 0
A68: GTH | B68: A | C68: =A68&B68 -> GTHA | D68: =VLOOKUP($C68,Asignaturas!$C$5:$D$261,2,0) -> JUANA MARÍA HUACO GARCÍA / TEO ERNESTO MARTIN HIDALGO CORTES / | E68: Práctica 2 | F68: AM | G68: 46136 | H68: 46139 | I68: 1:00p.m. | J68: =+Tabla2[[#This Row],[DÍA DE ENTREGA]]+8 -> 46144 | K68: VENTANILLA | L68: 0
A69: HC3 | B69: C | C69: =A69&B69 -> HC3C | D69: =VLOOKUP($C69,Asignaturas!$C$5:$D$261,2,0) -> ADRIANA ISABEL LAOS LEVAGGI / | E69: Práctica 1 | F69: AM | G69: 46136 | H69: 46139 | I69: 1:00p.m. | J69: =+Tabla2[[#This Row],[DÍA DE ENTREGA]]+8 -> 46144 | K69: CLASE | L69: =2+3 -> 5
A70: A1FZ4 | B70: A | C70: =A70&B70 -> A1FZ4A | D70: =VLOOKUP($C70,Asignaturas!$C$5:$D$261,2,0) -> ALVARO TRESIERRA / SERGIO REYES | E70: Práctica 1 | F70: PM | G70: 46135 | H70: 46136 | I70: 6:30p.m. | J70: =+Tabla2[[#This Row],[DÍA DE ENTREGA]]+8 -> 46143 | K70: CLASE | L70: 0
A71: DSO | B71: C | C71: =A71&B71 -> DSOC | D71: =VLOOKUP($C71,Asignaturas!$C$5:$D$261,2,0) -> JOSÉ LUIS CHINGUEL BELTRAN / | E71: Práctica 1 | F71: PM | G71: 46135 | H71: 46136 | I71: 6:30p.m. | J71: =+Tabla2[[#This Row],[DÍA DE ENTREGA]]+8 -> 46143 | K71: CLASE | L71: 1
A72: ESTA03006 | B72: A | C72: =A72&B72 -> ESTA03006A | D72: =VLOOKUP($C72,Asignaturas!$C$5:$D$261,2,0) -> GERMÁN ANTONIO VEGA ACUÑA / | E72: Control 01 | F72: AM | G72: 46135 | H72: 46136 | I72: 1:00p.m. | J72: =+Tabla2[[#This Row],[DÍA DE ENTREGA]]+8 -> 46143 | K72: CLASE | L72: 0
A73: AF2 | B73: A | C73: =A73&B73 -> AF2A | D73: =VLOOKUP($C73,Asignaturas!$C$5:$D$261,2,0) -> CLAUDIA MARÍA RIVERA TÁVARA / | E73: Práctica 1 | F73: AM | G73: 46136 | H73: 46139 | I73: 1:00p.m. | J73: =+Tabla2[[#This Row],[DÍA DE ENTREGA]]+8 -> 46144 | K73: CLASE | L73: 0
A74: DSO | B74: A | C74: =A74&B74 -> DSOA | D74: =VLOOKUP($C74,Asignaturas!$C$5:$D$261,2,0) -> RENATO CÁRCAMO SEMINARIO / | E74: Práctica 1 | F74: PM | G74: 46136 | H74: 46139 | I74: 6:30p.m. | J74: =+Tabla2[[#This Row],[DÍA DE ENTREGA]]+8 -> 46144 | K74: CLASE | L74: 4
A75: DSO | B75: B | C75: =A75&B75 -> DSOB | D75: =VLOOKUP($C75,Asignaturas!$C$5:$D$261,2,0) -> RENATO CÁRCAMO SEMINARIO / | E75: Práctica 1 | F75: PM | G75: 46136 | H75: 46139 | I75: 6:30p.m. | J75: =+Tabla2[[#This Row],[DÍA DE ENTREGA]]+8 -> 46144 | K75: VENTANILLA | L75: 2
A76: A1ST1 | B76: A | C76: =A76&B76 -> A1ST1A | D76: =VLOOKUP($C76,Asignaturas!$C$5:$D$261,2,0) -> PATRICIA ELBA SOTO QUIROGA / | E76: Práctica 1 | F76: PM | G76: 46139 | H76: 46140 | I76: 6:30p.m. | J76: =+Tabla2[[#This Row],[DÍA DE ENTREGA]]+8 -> 46147 | K76: CLASE | L76: 0
A77: A1OP1 | B77: B | C77: =A77&B77 -> A1OP1B | D77: =VLOOKUP($C77,Asignaturas!$C$5:$D$261,2,0) -> EDUARDO ALONSO SANCHEZ RUIZ / | E77: Práctica 1 | F77: PM | G77: 46139 | H77: 46140 | I77: 6:30p.m. | J77: =+Tabla2[[#This Row],[DÍA DE ENTREGA]]+8 -> 46147 | K77: CLASE | L77: 0
A78: A1OP1 | B78: A | C78: =A78&B78 -> A1OP1A | D78: =VLOOKUP($C78,Asignaturas!$C$5:$D$261,2,0) -> EDUARDO ALONSO SANCHEZ RUIZ / | E78: Práctica 1 | F78: AM | G78: 46140 | H78: 46141 | I78: 1:00p.m. | J78: =+Tabla2[[#This Row],[DÍA DE ENTREGA]]+8 -> 46148 | K78: VENTANILLA | L78: 1
A79: A1CF1 | B79: A | C79: =A79&B79 -> A1CF1A | D79: =VLOOKUP($C79,Asignaturas!$C$5:$D$261,2,0) -> MARIA ELENA ARCE ALMENARA / | E79: Práctica 1 | F79: PM | G79: 46141 | H79: 46142 | I79: 1:00p.m. | J79: =+Tabla2[[#This Row],[DÍA DE ENTREGA]]+8 -> 46149 | K79: VENTANILLA | L79: 2 | M79: AÚN NO LLEGAN SOBRANTES
A80: A1EC1 | B80: B | C80: =A80&B80 -> A1EC1B | D80: =VLOOKUP($C80,Asignaturas!$C$5:$D$261,2,0) -> INGRID CECILIA CASANA ORTEGA / | E80: Práctica 2 | F80: PM | G80: 46140 | H80: 46141 | I80: 6:30p.m. | J80: =+Tabla2[[#This Row],[DÍA DE ENTREGA]]+8 -> 46148 | K80: CLASE | L80: 2 | M80: AÚN NO LLEGAN SOBRANTES
A81: A1ST1 | B81: B | C81: =A81&B81 -> A1ST1B | D81: =VLOOKUP($C81,Asignaturas!$C$5:$D$261,2,0) -> PATRICIA ELBA SOTO QUIROGA / | E81: Práctica 1 | F81: PM | G81: 46140 | H81: 46141 | I81: 6:30p.m. | J81: =+Tabla2[[#This Row],[DÍA DE ENTREGA]]+8 -> 46148 | K81: CLASE | L81: =3+1 -> 4
A82: A1ES1 | B82: B | C82: =A82&B82 -> A1ES1B | D82: =VLOOKUP($C82,Asignaturas!$C$5:$D$261,2,0) -> DIANA LORENA SALAZAR TORRES / | E82: Práctica 2 | F82: PM | G82: 46140 | H82: 46141 | I82: 6:30p.m. | J82: =+Tabla2[[#This Row],[DÍA DE ENTREGA]]+8 -> 46148 | K82: CLASE | L82: 1
A83: ETC | B83: A | C83: =A83&B83 -> ETCA | D83: =VLOOKUP($C83,Asignaturas!$C$5:$D$261,2,0) -> DAVID TELLEZ MAQUEO / | E83: Práctica 1 | F83: PM | G83: 46140 | H83: 46141 | I83: 6:30p.m. | J83: =+Tabla2[[#This Row],[DÍA DE ENTREGA]]+8 -> 46148 | K83: CLASE | L83: 0
A84: A1EC1 | B84: A | C84: =A84&B84 -> A1EC1A | D84: =VLOOKUP($C84,Asignaturas!$C$5:$D$261,2,0) -> INGRID CECILIA CASANA ORTEGA / | E84: Práctica 2 | F84: PM | G84: 46140 | H84: 46141 | I84: 6:30p.m. | J84: =+Tabla2[[#This Row],[DÍA DE ENTREGA]]+8 -> 46148 | K84: CLASE | L84: 7
A85: A1IPN | B85: B | C85: =A85&B85 -> A1IPNB | D85: =VLOOKUP($C85,Asignaturas!$C$5:$D$261,2,0) -> WILLIAN ALFREDO REYES CORTES / | E85: Práctica 1 | F85: PM | G85: 46140 | H85: 46141 | I85: 6:30p.m. | J85: =+Tabla2[[#This Row],[DÍA DE ENTREGA]]+8 -> 46148 | K85: CLASE | L85: 0
A86: A1FP1 | B86: A | C86: =A86&B86 -> A1FP1A | D86: =VLOOKUP($C86,Asignaturas!$C$5:$D$261,2,0) -> WILLIAN ALFREDO REYES CORTES / | E86: Práctica 1 | F86: PM | G86: 46140 | H86: 46141 | I86: 6:30p.m. | J86: =+Tabla2[[#This Row],[DÍA DE ENTREGA]]+8 -> 46148 | K86: CLASE | L86: 0
A87: A1FP1 | B87: B | C87: =A87&B87 -> A1FP1B | D87: =VLOOKUP($C87,Asignaturas!$C$5:$D$261,2,0) -> WILLIAN ALFREDO REYES CORTES / | E87: Práctica 1 | F87: PM | G87: 46140 | H87: 46141 | I87: 6:30p.m. | J87: =+Tabla2[[#This Row],[DÍA DE ENTREGA]]+8 -> 46148 | K87: CLASE | L87: 0
A88: ESTA03005 | B88: A | C88: =A88&B88 -> ESTA03005A | D88: =VLOOKUP($C88,Asignaturas!$C$5:$D$261,2,0) -> RANDY JOEL FERNÁNDEZ PALOMINO / | E88: Práctica 1 | F88: PM | G88: 46140 | H88: 46141 | I88: 6:30p.m. | J88: =+Tabla2[[#This Row],[DÍA DE ENTREGA]]+8 -> 46148 | K88: CLASE | L88: 1
A89: A1MT3 | B89: A | C89: =A89&B89 -> A1MT3A | D89: =VLOOKUP($C89,Asignaturas!$C$5:$D$261,2,0) -> JAIME GERARDO VILLASANTE ABRAMONTE / | E89: Práctica 1 | F89: PM | G89: 46140 | H89: 46141 | I89: 6:30p.m. | J89: =+Tabla2[[#This Row],[DÍA DE ENTREGA]]+8 -> 46148 | K89: CLASE | L89: 0
A90: A1MT3 | B90: B | C90: =A90&B90 -> A1MT3B | D90: =VLOOKUP($C90,Asignaturas!$C$5:$D$261,2,0) -> JAIME GERARDO VILLASANTE ABRAMONTE / | E90: Práctica 1 | F90: PM | G90: 46140 | H90: 46141 | I90: 6:30p.m. | J90: =+Tabla2[[#This Row],[DÍA DE ENTREGA]]+8 -> 46148 | K90: CLASE | L90: 2
A91: MICR03005 | B91: A | C91: =A91&B91 -> MICR03005A | D91: =VLOOKUP($C91,Asignaturas!$C$5:$D$261,2,0) -> ALFONSO GUILLERMO DULANTO RISHING / | E91: Práctica 1 | F91: AM | G91: 46132 | H91: 46133 | I91: 1:00p.m. | J91: =+Tabla2[[#This Row],[DÍA DE ENTREGA]]+8 -> 46140 | K91: CLASE | L91: 0
A92: A1GP1 | B92: A | C92: =A92&B92 -> A1GP1A | D92: =VLOOKUP($C92,Asignaturas!$C$5:$D$261,2,0) -> MARTHA MARINA CASAS CASAS / | E92: Práctica 1 | F92: PM | G92: 46140 | H92: 46141 | I92: 6:30p.m. | J92: =+Tabla2[[#This Row],[DÍA DE ENTREGA]]+8 -> 46148 | K92: CLASE | L92: 0
A93: A1GP1 | B93: B | C93: =A93&B93 -> A1GP1B | D93: =VLOOKUP($C93,Asignaturas!$C$5:$D$261,2,0) -> MARTHA MARINA CASAS CASAS / | E93: Práctica 1 | F93: PM | G93: 46140 | H93: 46141 | I93: 6:30p.m. | J93: =+Tabla2[[#This Row],[DÍA DE ENTREGA]]+8 -> 46148 | K93: CLASE | L93: 2
A94: A1DPRT9 | B94: A | C94: =A94&B94 -> A1DPRT9A | D94: =VLOOKUP($C94,Asignaturas!$C$5:$D$261,2,0) -> MANUEL PRENDES GUARDIOLA / | E94: Práctica 2 | F94: PM | G94: 46140 | H94: 46141 | I94: 6:30p.m. | J94: =+Tabla2[[#This Row],[DÍA DE ENTREGA]]+8 -> 46148 | K94: CLASE | L94: 0
A95: A1EC2 | B95: A | C95: =A95&B95 -> A1EC2A | D95: =VLOOKUP($C95,Asignaturas!$C$5:$D$261,2,0) -> FRANCISCO LEVI TRUJILLO VARGAS / | E95: Práctica 1 | F95: AM | G95: 46141 | H95: 46142 | I95: 1:00p.m. | J95: =+Tabla2[[#This Row],[DÍA DE ENTREGA]]+8 -> 46149 | K95: CLASE | L95: =1+1 -> 2
A96: RCO | B96: B | C96: =A96&B96 -> RCOB | D96: =VLOOKUP($C96,Asignaturas!$C$5:$D$261,2,0) -> GONZALO ALEJANDRO FLORES CASTRO LINGAN / NAVARRO UBEDA GUILLERMO | E96: Práctica 1 | F96: AM | G96: 46141 | H96: 46142 | I96: 1:00p.m. | J96: =+Tabla2[[#This Row],[DÍA DE ENTREGA]]+8 -> 46149 | K96: CLASE | L96: 0
A97: A1CC1 | B97: B | C97: =A97&B97 -> A1CC1B | D97: =VLOOKUP($C97,Asignaturas!$C$5:$D$261,2,0) -> YULLIANA MARISED LLAUCE ONTANEDA / | E97: Práctica 1 | F97: AM | G97: 46141 | H97: 46142 | I97: 1:00p.m. | J97: =+Tabla2[[#This Row],[DÍA DE ENTREGA]]+8 -> 46149 | K97: CLASE | L97: 0
A98: A1CC1 | B98: B | C98: =A98&B98 -> A1CC1B | D98: =VLOOKUP($C98,Asignaturas!$C$5:$D$261,2,0) -> YULLIANA MARISED LLAUCE ONTANEDA / | E98: Control 01 | F98: AM | G98: 46141 | H98: 46142 | I98: 1:00p.m. | J98: =+Tabla2[[#This Row],[DÍA DE ENTREGA]]+8 -> 46149 | K98: CLASE | L98: 0
A99: A1CC1 | B99: B | C99: =A99&B99 -> A1CC1B | D99: =VLOOKUP($C99,Asignaturas!$C$5:$D$261,2,0) -> YULLIANA MARISED LLAUCE ONTANEDA / | E99: Taller 01 | F99: AM | G99: 46141 | H99: 46142 | I99: 1:00p.m. | J99: =+Tabla2[[#This Row],[DÍA DE ENTREGA]]+8 -> 46149 | K99: CLASE | L99: 0
A100: MATE03009 | B100: A | C100: =A100&B100 -> MATE03009A | D100: =VLOOKUP($C100,Asignaturas!$C$5:$D$261,2,0) -> NESTOR FARÍAS / WILLIAN REYES | E100: Práctica 2 | F100: AM | G100: 46141 | H100: 46142 | I100: 1:00p.m. | J100: =+Tabla2[[#This Row],[DÍA DE ENTREGA]]+8 -> 46149 | K100: VENTANILLA | L100: 0
A101: FINZ03032 | B101: A | C101: =A101&B101 -> FINZ03032A | D101: =VLOOKUP($C101,Asignaturas!$C$5:$D$261,2,0) -> BRENDA SILUPÚ GARCÉS / SERGIO DAVID REYES LANDA / | E101: Práctica 2 | F101: AM | G101: 46141 | H101: 46142 | I101: 1:00p.m. | J101: =+Tabla2[[#This Row],[DÍA DE ENTREGA]]+8 -> 46149 | K101: CLASE | L101: 4
A102: A1ES1 | B102: A | C102: =A102&B102 -> A1ES1A | D102: =VLOOKUP($C102,Asignaturas!$C$5:$D$261,2,0) -> RICARDO ALBERTO ORMEÑO SÁNCHEZ / | E102: Práctica 2 | F102: AM | G102: 46140 | H102: 46141 | I102: 1:00p.m. | J102: =+Tabla2[[#This Row],[DÍA DE ENTREGA]]+8 -> 46148 | K102: CLASE | L102: 3
A103: MACR03002 | B103: A | C103: =A103&B103 -> MACR03002A | D103: =VLOOKUP($C103,Asignaturas!$C$5:$D$261,2,0) -> LUIS ALONSO CASAVERDE ANTÓN / | E103: Práctica 2 | F103: PM | G103: 46140 | H103: 46141 | I103: 6:30p.m. | J103: =+Tabla2[[#This Row],[DÍA DE ENTREGA]]+8 -> 46148 | K103: CLASE | L103: 16
A104: A1LOG | B104: B | C104: =A104&B104 -> A1LOGB | D104: =VLOOKUP($C104,Asignaturas!$C$5:$D$261,2,0) -> NESTOR JAVIER FARIAS MORCILLO / | E104: Práctica 1 | F104: AM | G104: 46141 | H104: 46142 | I104: 1:00p.m. | J104: =+Tabla2[[#This Row],[DÍA DE ENTREGA]]+8 -> 46149 | K104: CLASE | L104: 0
A105: A1LOG | B105: A | C105: =A105&B105 -> A1LOGA | D105: =VLOOKUP($C105,Asignaturas!$C$5:$D$261,2,0) -> NESTOR JAVIER FARIAS MORCILLO / | E105: Práctica 1 | F105: AM | G105: 46141 | H105: 46142 | I105: 1:00p.m. | J105: =+Tabla2[[#This Row],[DÍA DE ENTREGA]]+8 -> 46149 | K105: CLASE | L105: 1
A106: ETC | B106: B | C106: =A106&B106 -> ETCB | D106: =VLOOKUP($C106,Asignaturas!$C$5:$D$261,2,0) -> DAVID ESPINOZA SOMOCURCIO / | E106: Práctica 1 | F106: AM | G106: 46141 | H106: 46142 | I106: 1:00p.m. | J106: =+Tabla2[[#This Row],[DÍA DE ENTREGA]]+8 -> 46149 | K106: CLASE | L106: 9
A107: HC3 | B107: B | C107: =A107&B107 -> HC3B | D107: =VLOOKUP($C107,Asignaturas!$C$5:$D$261,2,0) -> VICTOR VELEZMORO MONTES / | E107: Práctica 1 | F107: AM | G107: 46141 | H107: 46142 | I107: 1:00p.m. | J107: =+Tabla2[[#This Row],[DÍA DE ENTREGA]]+8 -> 46149 | K107: CLASE | L107: 0
... A110: HC1 | B110: E | C110: =A110&B110 -> HC1E | D110: =VLOOKUP($C110,Asignaturas!$C$5:$D$261,2,0) -> JOSE LUIS BELLIDO NINA / | E110: Práctica 2 | F110: PM | G110: 46141 | H110: 46142 | I110: 6:30p.m. | J110: =+Tabla2[[#This Row],[DÍA DE ENTREGA]]+8 -> 46149 | K110: VENTANILLA | L110: 5
A111: ESTA03008 | B111: A | C111: =A111&B111 -> ESTA03008A | D111: =VLOOKUP($C111,Asignaturas!$C$5:$D$261,2,0) -> CRISTIAN ADDERLY MARAVI MENESES / | E111: Práctica 2 | F111: PM | G111: 46140 | H111: 46141 | I111: 6:30p.m. | J111: =+Tabla2[[#This Row],[DÍA DE ENTREGA]]+8 -> 46148 | K111: CLASE | L111: 1 | M111: AÚN NO LLEGAN SOBRANTES
A112: A1CC1 | B112: A | C112: =A112&B112 -> A1CC1A | D112: =VLOOKUP($C112,Asignaturas!$C$5:$D$261,2,0) -> JORGE ARMANDO SANCHEZ FARFAN / | E112: Práctica 1 | F112: PM | G112: 46140 | H112: 46141 | I112: 6:30p.m. | J112: =+Tabla2[[#This Row],[DÍA DE ENTREGA]]+8 -> 46148 | K112: CLASE | L112: 1
A113: A1CF2 | B113: A | C113: =A113&B113 -> A1CF2A | D113: =VLOOKUP($C113,Asignaturas!$C$5:$D$261,2,0) -> MARLON RAUL ALVIA SIANCAS / | E113: Control 02 | F113: AM | G113: 46142 | H113: 46146 | I113: 1:00p.m. | J113: =+Tabla2[[#This Row],[DÍA DE ENTREGA]]+8 -> 46150 | K113: CLASE | L113: 0
A114: A1CF2 | B114: B | C114: =A114&B114 -> A1CF2B | D114: =VLOOKUP($C114,Asignaturas!$C$5:$D$261,2,0) -> MARLON RAUL ALVIA SIANCAS / | E114: Control 02 | F114: AM | G114: 46142 | H114: 46146 | I114: 1:00p.m. | J114: =+Tabla2[[#This Row],[DÍA DE ENTREGA]]+8 -> 46150 | K114: CLASE | L114: 0
A115: ESTA03005 | B115: A | C115: =A115&B115 -> ESTA03005A | D115: =VLOOKUP($C115,Asignaturas!$C$5:$D$261,2,0) -> RANDY JOEL FERNÁNDEZ PALOMINO / | E115: Práctica 2 | F115: AM | G115: 46142 | H115: 46146 | I115: 1:00p.m. | J115: =+Tabla2[[#This Row],[DÍA DE ENTREGA]]+8 -> 46150 | K115: CLASE | L115: 1
A116: A1MT1 | B116: A | C116: =A116&B116 -> A1MT1A | D116: =VLOOKUP($C116,Asignaturas!$C$5:$D$261,2,0) -> DIANA LORENA SALAZAR TORRES / | E116: Práctica 2 | F116: PM | G116: 46141 | H116: 46142 | I116: 6:30p.m. | J116: =+Tabla2[[#This Row],[DÍA DE ENTREGA]]+8 -> 46149 | K116: CLASE | L116: 1
A117: A1MT1 | B117: B | C117: =A117&B117 -> A1MT1B | D117: =VLOOKUP($C117,Asignaturas!$C$5:$D$261,2,0) -> DIANA LORENA SALAZAR TORRES / | E117: Práctica 2 | F117: PM | G117: 46141 | H117: 46142 | I117: 6:30p.m. | J117: =+Tabla2[[#This Row],[DÍA DE ENTREGA]]+8 -> 46149 | K117: CLASE | L117: 0
A118: A1ES2 | B118: A | C118: =A118&B118 -> A1ES2A | D118: =VLOOKUP($C118,Asignaturas!$C$5:$D$261,2,0) -> LUIS EGBERTO ALVARADO PINTADO / | E118: Práctica 1 | F118: AM | G118: 46142 | H118: 46146 | I118: 1:00p.m. | J118: =+Tabla2[[#This Row],[DÍA DE ENTREGA]]+8 -> 46150 | K118: VENTANILLA | L118: 3
A119: A1ES2 | B119: B | C119: =A119&B119 -> A1ES2B | D119: =VLOOKUP($C119,Asignaturas!$C$5:$D$261,2,0) -> LUIS EGBERTO ALVARADO PINTADO / | E119: Práctica 1 | F119: AM | G119: 46142 | H119: 46146 | I119: 1:00p.m. | J119: =+Tabla2[[#This Row],[DÍA DE ENTREGA]]+8 -> 46150 | K119: VENTANILLA | L119: 3
A120: A1MT2 | B120: A | C120: =A120&B120 -> A1MT2A | D120: =VLOOKUP($C120,Asignaturas!$C$5:$D$261,2,0) -> JORGE LUIS MARTINEZ PEREZ | E120: Práctica 2 | F120: AM | G120: 46142 | H120: 46146 | I120: 1:00p.m. | J120: =+Tabla2[[#This Row],[DÍA DE ENTREGA]]+8 -> 46150 | K120: VENTANILLA | L120: 1
A121: A1MT2 | B121: B | C121: =A121&B121 -> A1MT2B | D121: =VLOOKUP($C121,Asignaturas!$C$5:$D$261,2,0) -> JORGE LUIS MARTINEZ PEREZ | E121: Práctica 2 | F121: PM | G121: 46141 | H121: 46142 | I121: 6:30p.m. | J121: =+Tabla2[[#This Row],[DÍA DE ENTREGA]]+8 -> 46149 | K121: CLASE | L121: 0
A122: MT2 | B122: C | C122: =A122&B122 -> MT2C | D122: =VLOOKUP($C122,Asignaturas!$C$5:$D$261,2,0) -> JORGE LUIS MARTINEZ PEREZ | E122: Práctica 2 | F122: PM | G122: 46141 | H122: 46142 | I122: 6:30p.m. | J122: =+Tabla2[[#This Row],[DÍA DE ENTREGA]]+8 -> 46149 | K122: CLASE | L122: 0
A123: LC1 | B123: E | C123: =A123&B123 -> LC1E | D123: =VLOOKUP($C123,Asignaturas!$C$5:$D$261,2,0) -> MANUEL PRENDES GUARDIOLA / | E123: Práctica 1 | F123: AM | G123: 46142 | H123: 46146 | I123: 1:00p.m. | J123: =+Tabla2[[#This Row],[DÍA DE ENTREGA]]+8 -> 46150 | K123: CLASE | L123: 1
... A163: A1FZ3 | B163: B | C163: =A163&B163 -> A1FZ3B | D163: =VLOOKUP($C163,Asignaturas!$C$5:$D$261,2,0) -> JORGE EDUARDO GALLO COSTA / | E163: Evaluación corta 2 | F163: PM | G163: 46142 | H163: 46146 | I163: 6:30p.m. | J163: =+Tabla2[[#This Row],[DÍA DE ENTREGA]]+8 -> 46150 | K163: CLASE | L163: 0
A164: A1GP2 | B164: B | C164: =A164&B164 -> A1GP2B | D164: =VLOOKUP($C164,Asignaturas!$C$5:$D$261,2,0) -> JACQUELINE MARIELA GARCÍA ROJAS / | E164: Práctica 1 | F164: AM | G164: 46146 | H164: 46147 | I164: 1:00p.m. | J164: =+Tabla2[[#This Row],[DÍA DE ENTREGA]]+8 -> 46154 | K164: CLASE | L164: 1 | M164: AUN NO LLEGAN SOBRANTES
A165: MICR03006 | B165: A | C165: =A165&B165 -> MICR03006A | D165: =VLOOKUP($C165,Asignaturas!$C$5:$D$261,2,0) -> VANIA SALAS GARCIA / | E165: Práctica 2 | F165: AM | G165: 46146 | H165: 46147 | I165: 1:00p.m. | J165: =+Tabla2[[#This Row],[DÍA DE ENTREGA]]+8 -> 46154 | K165: CLASE | L165: 2
A166: A1ES2 | B166: A | C166: =A166&B166 -> A1ES2A | D166: =VLOOKUP($C166,Asignaturas!$C$5:$D$261,2,0) -> LUIS EGBERTO ALVARADO PINTADO / | E166: Control 01 | F166: PM | G166: 46146 | H166: 46147 | I166: 6:30p.m. | J166: =+Tabla2[[#This Row],[DÍA DE ENTREGA]]+8 -> 46154 | K166: CLASE | L166: 1
A167: A1CF1 | B167: A | C167: =A167&B167 -> A1CF1A | D167: =VLOOKUP($C167,Asignaturas!$C$5:$D$261,2,0) -> MARIA ELENA ARCE ALMENARA / | E167: Práctica 2 | F167: AM | G167: 46147 | H167: 46148 | I167: 1:00p.m. | J167: =+Tabla2[[#This Row],[DÍA DE ENTREGA]]+8 -> 46155 | K167: VENTANILLA | L167: 1
A168: A1AG4 | B168: A | C168: =A168&B168 -> A1AG4A | D168: =VLOOKUP($C168,Asignaturas!$C$5:$D$261,2,0) -> JUANA MARÍA HUACO GARCÍA / | E168: Práctica 1 | F168: AM | G168: 46147 | H168: 46148 | I168: 1:00p.m. | J168: =+Tabla2[[#This Row],[DÍA DE ENTREGA]]+8 -> 46155 | K168: VENTANILLA | L168: 1
A169: A1AG4 | B169: B | C169: =A169&B169 -> A1AG4B | D169: =VLOOKUP($C169,Asignaturas!$C$5:$D$261,2,0) -> JUANA MARÍA HUACO GARCÍA / | E169: Práctica 1 | F169: AM | G169: 46147 | H169: 46148 | I169: 1:00p.m. | J169: =+Tabla2[[#This Row],[DÍA DE ENTREGA]]+8 -> 46155 | K169: VENTANILLA | L169: 0
A170: LC1 | B170: A | C170: =A170&B170 -> LC1A | D170: =VLOOKUP($C170,Asignaturas!$C$5:$D$261,2,0) -> ROSA DE JESÚS BOBBIO ALVAREZ / | E170: Práctica 1 | F170: AM | G170: 46147 | H170: 46148 | I170: 1:00p.m. | J170: =+Tabla2[[#This Row],[DÍA DE ENTREGA]]+8 -> 46155 | K170: VENTANILLA | L170: 0
A171: HC1 | B171: A | C171: =A171&B171 -> HC1A | D171: =VLOOKUP($C171,Asignaturas!$C$5:$D$261,2,0) -> CRISTINA VARGAS PACHECO / | E171: Práctica 2 | F171: AM | G171: 46147 | H171: 46148 | I171: 1:00p.m. | J171: =+Tabla2[[#This Row],[DÍA DE ENTREGA]]+8 -> 46155 | K171: VENTANILLA | L171: 0
...

Sheet RECLAMOS
A2: RECLAMOS POR RECOGER
A4: SIGLA | B4: SECC | C4: BUSCAR | D4: DOCENTE | E4: EVALUACIÓN | F4: TURNO | G4: DÍA DE ENTREGA | H4: VENCIMIENTO PARA 2° RECLAMO | I4: HORA | J4: CANTIDAD 2°RECLAMOS | K4: OBSERVACIÓN
A5: A1MK2 | B5: A | C5: =A5&B5 -> A1MK2A | D5: =VLOOKUP($C5,Asignaturas!$C$5:$D$261,2,0) -> VICTOR ALEJANDRO DE LA TORRE PALACIOS / | E5: Control 01 | F5: AM | G5: 46128 | H5: 46129 | I5: 1:00 p.m.
A6: A1DPRT9 | B6: A | C6: =A6&B6 -> A1DPRT9A | D6: =VLOOKUP($C6,Asignaturas!$C$5:$D$261,2,0) -> MANUEL PRENDES GUARDIOLA / | E6: Práctica 1 | F6: AM | G6: 46134 | H6: 46135 | I6: 1:00 p.m.
A7: MATE03009 | B7: A | C7: =A7&B7 -> MATE03009A | D7: =VLOOKUP($C7,Asignaturas!$C$5:$D$261,2,0) -> NESTOR FARÍAS / WILLIAN REYES | E7: Práctica 1 | F7: AM | G7: 46134 | H7: 46135 | I7: 1:00 p.m.
A8: A1FZ3 | B8: A | C8: =A8&B8 -> A1FZ3A | D8: =VLOOKUP($C8,Asignaturas!$C$5:$D$261,2,0) -> JORGE EDUARDO GALLO COSTA / | E8: Práctica 1 | F8: AM | G8: 46135 | H8: 46135 | I8: 1:00 p.m.
A9: A1CC1 | B9: A | C9: =A9&B9 -> A1CC1A | D9: =VLOOKUP($C9,Asignaturas!$C$5:$D$261,2,0) -> JORGE ARMANDO SANCHEZ FARFAN / | E9: Control 01 | F9: AM | G9: 46135 | H9: 46135 | I9: 1:00 p.m.
A10: MATE03010 | B10: A | C10: =A10&B10 -> MATE03010A | D10: =VLOOKUP($C10,Asignaturas!$C$5:$D$261,2,0) -> RANDY JOEL FERNÁNDEZ PALOMINO / | E10: Práctica 1 | F10: AM | G10: 46135 | H10: 46135 | I10: 1:00 p.m.
A11: MATE03008 | B11: B | C11: =A11&B11 -> MATE03008B | D11: =VLOOKUP($C11,Asignaturas!$C$5:$D$261,2,0) -> JAVIER FARFÁN NAVARRO / | E11: Práctica 1 | F11: PM | G11: 46135 | H11: 46135 | I11: 6:00 p.m.
A12: MATE03008 | B12: C | C12: =A12&B12 -> MATE03008C | D12: =VLOOKUP($C12,Asignaturas!$C$5:$D$261,2,0) -> JAVIER FARFÁN NAVARRO / | E12: Práctica 1 | F12: PM | G12: 46135 | H12: 46135 | I12: 6:00 p.m.
A13: HC1 | B13: C | C13: =A13&B13 -> HC1C | D13: =VLOOKUP($C13,Asignaturas!$C$5:$D$261,2,0) -> ADRIANA ISABEL LAOS LEVAGGI / | E13: Práctica 1 | F13: AM | G13: 46136 | H13: 46139 | I13: 1:00 p.m.
A14: MATE03008 | B14: A | C14: =A14&B14 -> MATE03008A | D14: =VLOOKUP($C14,Asignaturas!$C$5:$D$261,2,0) -> JAVIER FARFÁN NAVARRO / | E14: Práctica 1 | F14: AM | G14: 46140 | H14: 46141 | I14: 1:00 p.m.
A15: A1FZ1 | B15: A | C15: =A15&B15 -> A1FZ1A | D15: =VLOOKUP($C15,Asignaturas!$C$5:$D$261,2,0) -> JUAN RICARDO MATÍAS PALMA / | E15: Práctica 1 | F15: AM | G15: 46140 | H15: 46141 | I15: 1:00 p.m.
A16: MATE03007 | B16: A | C16: =A16&B16 -> MATE03007A | D16: =VLOOKUP($C16,Asignaturas!$C$5:$D$261,2,0) -> CARLOS IMÁN ANCAJIMA / | E16: Práctica 1 | F16: AM | G16: 46140 | H16: 46141 | I16: 1:00 p.m.
... A51: HC1 | B51: C | C51: =A51&B51 -> HC1C | D51: =VLOOKUP($C51,Asignaturas!$C$5:$D$261,2,0) -> ADRIANA ISABEL LAOS LEVAGGI / | E51: Práctica 2 | F51: PM | G51: 46150 | H51: 46153 | I51: 6:00 p.m.
C52: =A52&B52 | D52: =VLOOKUP($C52,Asignaturas!$C$5:$D$261,2,0) -> 0
C53: =A53&B53 | D53: =VLOOKUP($C53,Asignaturas!$C$5:$D$261,2,0) -> 0
C54: =A54&B54 | D54: =VLOOKUP($C54,Asignaturas!$C$5:$D$261,2,0) -> 0
C55: =A55&B55 | D55: =VLOOKUP($C55,Asignaturas!$C$5:$D$261,2,0) -> 0
C56: =A56&B56 | D56: =VLOOKUP($C56,Asignaturas!$C$5:$D$261,2,0) -> 0
C57: =A57&B57 | D57: =VLOOKUP($C57,Asignaturas!$C$5:$D$261,2,0) -> 0
C58: =A58&B58 | D58: =VLOOKUP($C58,Asignaturas!$C$5:$D$261,2,0) -> 0
C59: =A59&B59 | D59: =VLOOKUP($C59,Asignaturas!$C$5:$D$261,2,0) -> 0
C60: =A60&B60 | D60: =VLOOKUP($C60,Asignaturas!$C$5:$D$261,2,0) -> 0
C61: =A61&B61 | D61: =VLOOKUP($C61,Asignaturas!$C$5:$D$261,2,0) -> 0
C62: =A62&B62 | D62: =VLOOKUP($C62,Asignaturas!$C$5:$D$261,2,0) -> 0
C63: =A63&B63 | D63: =VLOOKUP($C63,Asignaturas!$C$5:$D$261,2,0) -> 0
... C185: =A185&B185 | D185: =VLOOKUP($C185,Asignaturas!$C$5:$D$261,2,0) -> 0
C186: =A186&B186 | D186: =VLOOKUP($C186,Asignaturas!$C$5:$D$261,2,0) -> 0 | F186: AM | G186: 45982 | H186: 45985 | I186: 1:00 p.m.
C187: =A187&B187 | D187: =VLOOKUP($C187,Asignaturas!$C$5:$D$261,2,0) -> 0 | E187: PC3 | F187: PM | G187: 45982 | H187: 45985 | I187: 6:00 p.m.
C188: =A188&B188 | D188: =VLOOKUP($C188,Asignaturas!$C$5:$D$261,2,0) -> 0 | E188: PC3 | F188: AM | G188: 45985 | H188: 45986 | I188: 1:00 p.m.
C189: =A189&B189 | D189: =VLOOKUP($C189,Asignaturas!$C$5:$D$261,2,0) -> 0 | E189: PC3 | F189: AM | G189: 45985 | H189: 45986 | I189: 1:00 p.m.
C190: =A190&B190 | D190: =VLOOKUP($C190,Asignaturas!$C$5:$D$261,2,0) -> 0 | E190: PC3 | F190: AM | G190: 45985 | H190: 45986 | I190: 1:00 p.m.
C191: =A191&B191 | D191: =VLOOKUP($C191,Asignaturas!$C$5:$D$261,2,0) -> 0 | E191: PC4 | F191: AM | G191: 45985 | H191: 45986 | I191: 1:00 p.m.
C192: =A192&B192 | D192: =VLOOKUP($C192,Asignaturas!$C$5:$D$261,2,0) -> 0 | E192: PC3 | F192: PM | G192: 45985 | H192: 45986 | I192: 6:00 p.m.
C193: =A193&B193 | D193: =VLOOKUP($C193,Asignaturas!$C$5:$D$261,2,0) -> 0 | E193: PC3 | F193: PM | G193: 45985 | H193: 45986 | I193: 6:00 p.m.
C194: =A194&B194 | D194: =VLOOKUP($C194,Asignaturas!$C$5:$D$261,2,0) -> 0 | E194: PC3 | F194: PM | G194: 45985 | H194: 45986 | I194: 6:00 p.m.
C195: =A195&B195 | D195: =VLOOKUP($C195,Asignaturas!$C$5:$D$261,2,0) -> 0 | E195: PC2 | F195: AM | G195: 45986 | H195: 45987 | I195: 1:00 p.m.
C196: =A196&B196 | D196: =VLOOKUP($C196,Asignaturas!$C$5:$D$261,2,0) -> 0 | E196: PC2 | F196: AM | G196: 45986 | H196: 45987 | I196: 1:00 p.m.
C197: =A197&B197 | D197: =VLOOKUP($C197,Asignaturas!$C$5:$D$261,2,0) -> 0 | E197: PC3 | F197: PM | G197: 45986 | H197: 45987 | I197: 6:00 p.m.
C198: =A198&B198 | D198: =VLOOKUP($C198,Asignaturas!$C$5:$D$261,2,0) -> 0 | E198: PC2 | F198: PM | G198: 45986 | H198: 45987 | I198: 6:00 p.m.
... C234: =A234&B234 | D234: =VLOOKUP($C234,Asignaturas!$C$5:$D$261,2,0) -> 0 | E234: LABORATORIO | F234: PM | G234: 45993 | H234: 45994 | I234: 6:00 p.m.
C235: A1CF2A | D235: MARLON RAUL ALVIA SIANCAS / | E235: FINAL | F235: AM | G235: 45994 | H235: 45995 | I235: 1:00 p.m.
C236: A1AG4A | D236: JUANA MARÍA HUACO GARCÍA / | E236: PC3 | F236: AM | G236: 45994 | H236: 45995 | I236: 1:00 p.m.
C237: A1GP2A | D237: JACQUELINE MARIELA GARCÍA ROJAS / | E237: PC1 | F237: AM | G237: 45994 | H237: 45995 | I237: 1:00 p.m.
C238: A1GP1B | D238: MARTHA MARINA CASAS CASAS / | E238: PC3 | F238: AM | G238: 45994 | H238: 45995 | I238: 1:00 p.m.
C239: A1CF1A | D239: JUAN CARLOS ESTEBAN VALLE BENITES / | E239: FINAL | F239: AM | G239: 45994 | H239: 45995 | I239: 1:00 p.m.
C240: A1GP2A | D240: JACQUELINE MARIELA GARCÍA ROJAS / | E240: INFORME 2 | F240: AM | G240: 45994 | H240: 45995 | I240: 1:00 p.m.
C241: E2PMI1B | D241: ABRAHAM CRESCENCIO AGUILAR PONCE / | E241: PC4 | F241: AM | G241: 45994 | H241: 45995 | I241: 1:00 p.m.
C242: E2PMI1B | D242: ABRAHAM CRESCENCIO AGUILAR PONCE / | E242: PC3 | F242: AM | G242: 45994 | H242: 45995 | I242: 1:00 p.m.
C243: E2OPT1A | D243: ELLIS RODNEY HIDALGO MENDOZA / | E243: PC4 | F243: AM | G243: 45994 | H243: 45995 | I243: 1:00 p.m.
C244: E2OPT1B | D244: ELLIS RODNEY HIDALGO MENDOZA / | E244: PC4 | F244: AM | G244: 45994 | H244: 45995 | I244: 1:00 p.m.
C245: E2FIN1A | D245: ALVARO EDMUNDO TRESIERRA TANAKA / SERGIO DAVID REYES LANDA / | E245: PC4 | F245: PM | G245: 45994 | H245: 45995 | I245: 6:00 p.m.
C246: MLLA | D246: GONZALO ALEJANDRO FLORES CASTRO LINGAN / | E246: PC2 | F246: AM | G246: 45995 | H246: 45996 | I246: 1:00 p.m.
... C264: LC2C | D264: NELLY MARÍA TRELLES CASTRO / | E264: FINAL | F264: AM | G264: 45996 | H264: 45997 | I264: 1:00 p.m.
C265: =A265&B265 | D265: =VLOOKUP($C265,Asignaturas!$C$5:$D$261,2,0) -> 0 | E265: FINAL | F265: AM | G265: 45996 | H265: 45997 | I265: 1:00 p.m.
C266: =A266&B266 | D266: =VLOOKUP($C266,Asignaturas!$C$5:$D$261,2,0) -> 0 | E266: FINAL | F266: AM | G266: 45996 | H266: 45997 | I266: 1:00 p.m.
C267: =A267&B267 | D267: =VLOOKUP($C267,Asignaturas!$C$5:$D$261,2,0) -> 0 | E267: FINAL | F267: PM | G267: 45996 | H267: 45997 | I267: 6:00 p.m.
C268: =A268&B268 | D268: =VLOOKUP($C268,Asignaturas!$C$5:$D$261,2,0) -> 0 | E268: FINAL | F268: PM | G268: 45996 | H268: 45997 | I268: 6:00 p.m.
C269: =A269&B269 | D269: =VLOOKUP($C269,Asignaturas!$C$5:$D$261,2,0) -> 0 | E269: FINAL | F269: PM | G269: 45996 | H269: 45997 | I269: 6:00 p.m.
C270: =A270&B270 | D270: =VLOOKUP($C270,Asignaturas!$C$5:$D$261,2,0) -> 0 | E270: FINAL | F270: PM | G270: 45996 | H270: 45997 | I270: 6:00 p.m.
C271: =A271&B271 | D271: =VLOOKUP($C271,Asignaturas!$C$5:$D$261,2,0) -> 0 | E271: FINAL | F271: PM | G271: 45996 | H271: 45997 | I271: 6:00 p.m.
C272: =A272&B272 | D272: =VLOOKUP($C272,Asignaturas!$C$5:$D$261,2,0) -> 0 | E272: FINAL | F272: PM | G272: 45996 | H272: 46001 | I272: 1:00 p.m.
C273: =A273&B273 | D273: =VLOOKUP($C273,Asignaturas!$C$5:$D$261,2,0) -> 0 | E273: FINAL | F273: PM | G273: 45996 | H273: 46001 | I273: 1:00 p.m.
C274: =A274&B274 | D274: =VLOOKUP($C274,Asignaturas!$C$5:$D$261,2,0) -> 0 | E274: FINAL | F274: PM | G274: 45996 | H274: 46001 | I274: 1:00 p.m.
C275: =A275&B275 | D275: =VLOOKUP($C275,Asignaturas!$C$5:$D$261,2,0) -> 0 | E275: FINAL | F275: PM | G275: 45996 | H275: 46001 | I275: 1:00 p.m.
C276: =A276&B276 | D276: =VLOOKUP($C276,Asignaturas!$C$5:$D$261,2,0) -> 0 | E276: FINAL | F276: AM | G276: 45997 | H276: 46001 | I276: 1:00 p.m.
... C426: =A426&B426 | D426: =VLOOKUP($C426,Asignaturas!$C$5:$D$261,2,0) -> 0 | E426: SUSTITUTORIO | F426: AM | G426: 46009 | H426: 46009 | I426: 1:00 p.m.
C427: =A427&B427 | D427: =VLOOKUP($C427,Asignaturas!$C$5:$D$261,2,0) -> 0 | E427: SUSTITUTORIO | F427: AM | G427: 46009 | H427: 46009 | I427: 1:00 p.m. | M427: ¿
C428: =A428&B428 | D428: =VLOOKUP($C428,Asignaturas!$C$5:$D$261,2,0) -> 0 | E428: SUSTITUTORIO | F428: AM | G428: 46009 | H428: 46009 | I428: 1:00 p.m.
C429: =A429&B429 | D429: =VLOOKUP($C429,Asignaturas!$C$5:$D$261,2,0) -> 0 | E429: SUSTITUTORIO | F429: AM | G429: 46009 | H429: 46009 | I429: 1:00 p.m.
C430: =A430&B430 | D430: =VLOOKUP($C430,Asignaturas!$C$5:$D$261,2,0) -> 0 | E430: SUSTITUTORIO | F430: AM | G430: 46009 | H430: 46009 | I430: 1:00 p.m.
C431: =A431&B431 | D431: =VLOOKUP($C431,Asignaturas!$C$5:$D$261,2,0) -> 0 | E431: PC2 | F431: AM | G431: 46009 | H431: 46009 | I431: 1:00 p.m.
C432: =A432&B432 | D432: =VLOOKUP($C432,Asignaturas!$C$5:$D$261,2,0) -> 0 | E432: SUSTITUTORIO | F432: AM | G432: 46009 | H432: 46009 | I432: 1:00 p.m.
C433: =A433&B433 | D433: =VLOOKUP($C433,Asignaturas!$C$5:$D$261,2,0) -> 0 | E433: FINAL | F433: AM | G433: 46009 | H433: 46009 | I433: 1:00 p.m.
C434: =A434&B434 | D434: =VLOOKUP($C434,Asignaturas!$C$5:$D$261,2,0) -> 0 | E434: FINAL | F434: AM | G434: 46009 | H434: 46009 | I434: 1:00 p.m.
C435: =A435&B435 | D435: =VLOOKUP($C435,Asignaturas!$C$5:$D$261,2,0) -> 0 | E435: SUSTITUTORIO | F435: AM | G435: 46010 | H435: 46010 | I435: 11:00 a.m.
C436: =A436&B436 | D436: =VLOOKUP($C436,Asignaturas!$C$5:$D$261,2,0) -> 0 | E436: SUSTITUTORIO | F436: AM | G436: 46010 | H436: 46010 | I436: 11:00 a.m.
C437: =A437&B437 | D437: =VLOOKUP($C437,Asignaturas!$C$5:$D$261,2,0) -> 0 | E437: SUSTITUTORIO | F437: AM | G437: 46010 | H437: 46010 | I437: 11:00 a.m.
C438: =A438&B438 | D438: =VLOOKUP($C438,Asignaturas!$C$5:$D$261,2,0) -> 0 | E438: SUSTITUTORIO | F438: AM | G438: 46010 | H438: 46010 | I438: 11:00 a.m.
C439: =A439&B439 | D439: =VLOOKUP($C439,Asignaturas!$C$5:$D$261,2,0) -> 0 | E439: SUSTITUTORIO | F439: AM | G439: 46010 | H439: 46010 | I439: 11:00 a.m.
C440: =A440&B440 | D440: =VLOOKUP($C440,Asignaturas!$C$5:$D$261,2,0) -> 0
C441: =A441&B441 | D441: =VLOOKUP($C441,Asignaturas!$C$5:$D$261,2,0) -> 0
C442: =A442&B442 | D442: =VLOOKUP($C442,Asignaturas!$C$5:$D$261,2,0) -> 0
C443: =A443&B443 | D443: =VLOOKUP($C443,Asignaturas!$C$5:$D$261,2,0) -> 0
C444: =A444&B444 | D444: =VLOOKUP($C444,Asignaturas!$C$5:$D$261,2,0) -> 0
C445: =A445&B445 | D445: =VLOOKUP($C445,Asignaturas!$C$5:$D$261,2,0) -> 0
C446: =A446&B446 | D446: =VLOOKUP($C446,Asignaturas!$C$5:$D$261,2,0) -> 0
C447: =A447&B447 | D447: =VLOOKUP($C447,Asignaturas!$C$5:$D$261,2,0) -> 0
C448: =A448&B448 | D448: =VLOOKUP($C448,Asignaturas!$C$5:$D$261,2,0) -> 0
C449: =A449&B449 | D449: =VLOOKUP($C449,Asignaturas!$C$5:$D$261,2,0) -> 0
C450: =A450&B450 | D450: =VLOOKUP($C450,Asignaturas!$C$5:$D$261,2,0) -> 0
C451: =A451&B451 | D451: =VLOOKUP($C451,Asignaturas!$C$5:$D$261,2,0) -> 0
... C461: =A461&B461 | D461: =VLOOKUP($C461,Asignaturas!$C$5:$D$261,2,0) -> 0
C462: =A462&B462 | D462: =VLOOKUP($C462,Asignaturas!$C$5:$D$261,2,0) -> 0 | J462: 1
C463: =A463&B463 | D463: =VLOOKUP($C463,Asignaturas!$C$5:$D$261,2,0) -> 0
C464: =A464&B464 | D464: =VLOOKUP($C464,Asignaturas!$C$5:$D$261,2,0) -> 0
C465: =A465&B465 | D465: =VLOOKUP($C465,Asignaturas!$C$5:$D$261,2,0) -> 0
C466: =A466&B466 | D466: =VLOOKUP($C466,Asignaturas!$C$5:$D$261,2,0) -> 0

Sheet CONTRAreclamos
A2: CONTROL DE SEGUNDOS RECLAMOS 2025-I
A4: SIGLA | B4: APELLIDOS Y NOMBRES | C4: SECCIÓN | D4: BUSCAR | E4: PROFESOR de la asignatura | F4: EVALUACIÓN | G4: DIA DE ENTREGA por el alumno | H4: PROFESOR QUE CORREJIRÁ | I4: FECHA de recepción por quien corrije | J4: RESUELTO(CAMBIA NOTA) | K4: NP/P
D5: =A5&C5 | E5: =VLOOKUP(D5,Asignaturas!$C$5:$D$261,2,0) -> 0
D6: =A6&C6 | E6: =VLOOKUP(D6,Asignaturas!$C$5:$D$261,2,0) -> 0
D7: =A7&C7 | E7: =VLOOKUP(D7,Asignaturas!$C$5:$D$261,2,0) -> 0
D8: =A8&C8 | E8: =VLOOKUP(D8,Asignaturas!$C$5:$D$261,2,0) -> 0
D9: =A9&C9 | E9: =VLOOKUP(D9,Asignaturas!$C$5:$D$261,2,0) -> 0
D10: =A10&C10 | E10: =VLOOKUP(D10,Asignaturas!$C$5:$D$261,2,0) -> 0
D11: =A11&C11 | E11: =VLOOKUP(D11,Asignaturas!$C$5:$D$261,2,0) -> 0
D12: =A12&C12 | E12: =VLOOKUP(D12,Asignaturas!$C$5:$D$261,2,0) -> 0
D13: =A13&C13 | E13: =VLOOKUP(D13,Asignaturas!$C$5:$D$261,2,0) -> 0
D14: =A14&C14 | E14: =VLOOKUP(D14,Asignaturas!$C$5:$D$261,2,0) -> 0
D15: =A15&C15 | E15: =VLOOKUP(D15,Asignaturas!$C$5:$D$261,2,0) -> 0
D16: =A16&C16 | E16: =VLOOKUP(D16,Asignaturas!$C$5:$D$261,2,0) -> 0
... D54: =A54&C54 | E54: =VLOOKUP(D54,Asignaturas!$C$5:$D$261,2,0) -> 0
E55: =VLOOKUP(D55,Asignaturas!$C$5:$D$261,2,0) -> #N/A
E56: =VLOOKUP(D56,Asignaturas!$C$5:$D$261,2,0) -> #N/A
E57: =VLOOKUP(D57,Asignaturas!$C$5:$D$261,2,0) -> #N/A
E58: =VLOOKUP(D58,Asignaturas!$C$5:$D$261,2,0) -> #N/A
